mlflow_fr/__init__.py
mlflow_fr-1.0.0.dist-info/WHEEL
mlflow_fr-1.0.0.dist-info/entry_points.txt
mlflow_fr-1.0.0.dist-info/METADATA
mlflow_fr-1.0.0.dist-info/RECORD
