Metadata-Version: 2.3
Name: mlflow-fr
Version: 1.0.0
Summary: MLflow random run names in French
Author: Jean Plumail
Author-email: Jean Plumail <jean.plumail@yellowscan.com>
Requires-Dist: mlflow
Requires-Python: >=3.6
